nakivo_prometheus_exporter/__debug__.py
nakivo_prometheus_exporter/__init__.py
nakivo_prometheus_exporter/__version__.py
nakivo_prometheus_exporter/metrics.py
nakivo_prometheus_exporter/nakivo_api.py
nakivo_prometheus_exporter/prom_parser.py
nakivo_prometheus_exporter/server.py
nakivo_prometheus_exporter-0.3.0.dist-info/METADATA
nakivo_prometheus_exporter-0.3.0.dist-info/WHEEL
nakivo_prometheus_exporter-0.3.0.dist-info/entry_points.txt
nakivo_prometheus_exporter-0.3.0.dist-info/top_level.txt
nakivo_prometheus_exporter-0.3.0.dist-info/RECORD
