Metadata-Version: 2.1
Name: nakivo_prometheus_exporter
Version: 0.3.0
Summary: Connecto to Nakivo API and export metrics to Prometheus
Home-page: https://github.com/netinvent/nakivo_prometheus_exporter
Author: NetInvent - Orsiris de Jong
Author-email: contact@netinvent.fr
License: GPLv3
Keywords: shell,backup,prometheus,linux,cli
Classifier: Development Status :: 5 - Production/Stable
Classifier: Intended Audience :: End Users/Desktop
Classifier: Intended Audience :: System Administrators
Classifier: Intended Audience :: Information Technology
Classifier: Intended Audience :: Developers
Classifier: Intended Audience :: Science/Research
Classifier: Topic :: System :: Archiving :: Backup
Classifier: Topic :: System
Classifier: Topic :: System :: Monitoring
Classifier: Topic :: Utilities
Classifier: Programming Language :: Python
Classifier: Programming Language :: Python :: 3
Classifier: Programming Language :: Python :: 3.6
Classifier: Programming Language :: Python :: 3.7
Classifier: Programming Language :: Python :: 3.8
Classifier: Programming Language :: Python :: 3.9
Classifier: Programming Language :: Python :: 3.10
Classifier: Programming Language :: Python :: 3.11
Classifier: Programming Language :: Python :: Implementation :: CPython
Classifier: Programming Language :: Python :: Implementation :: PyPy
Classifier: Operating System :: POSIX :: Linux
Classifier: License :: OSI Approved :: GNU General Public License v3 (GPLv3)
Requires-Python: >=3.6
Requires-Dist: ruamel.yaml
Requires-Dist: ofunctions.requestor >=1.1.0
Requires-Dist: ofunctions.logger-utils
Requires-Dist: ofunctions.logger-utils >=2.4.0
Requires-Dist: gunicorn
Requires-Dist: uvicorn[standard]
Requires-Dist: fastapi
Requires-Dist: fastapi-offline >=1.5.0
Requires-Dist: pydantic ~=2.6.3
